MANIFEST.in
plugin_outlook.xml
setup.py
./__init__.py
./__openerp__.py
./plugin_outlook.py
i18n/ar.po
i18n/bg.po
i18n/ca.po
i18n/cs.po
i18n/da.po
i18n/de.po
i18n/el.po
i18n/es.po
i18n/es_CR.po
i18n/es_MX.po
i18n/es_VE.po
i18n/et.po
i18n/fi.po
i18n/fr.po
i18n/gl.po
i18n/hr.po
i18n/hu.po
i18n/id.po
i18n/it.po
i18n/ja.po
i18n/mk.po
i18n/mn.po
i18n/nb.po
i18n/nl.po
i18n/pl.po
i18n/plugin_outlook.pot
i18n/pt.po
i18n/pt_BR.po
i18n/ro.po
i18n/ru.po
i18n/sl.po
i18n/sr@latin.po
i18n/sv.po
i18n/tr.po
i18n/zh_CN.po
images/config_outlook.jpeg
images/outlook_config_openerp.jpeg
images/outlook_push.jpeg
openerp_plugin_outlook.egg-info/PKG-INFO
openerp_plugin_outlook.egg-info/SOURCES.txt
openerp_plugin_outlook.egg-info/dependency_links.txt
openerp_plugin_outlook.egg-info/requires.txt
openerp_plugin_outlook.egg-info/top_level.txt
static/openerp-outlook-plugin/OpenERPOutlookPlugin/Resources/195737_152643643962_3595480_n.jpg
static/openerp-outlook-plugin/OpenERPOutlookPlugin/Resources/Account.ico
static/openerp-outlook-plugin/OpenERPOutlookPlugin/Resources/Account.png
static/openerp-outlook-plugin/OpenERPOutlookPlugin/Resources/Archive.png
static/openerp-outlook-plugin/OpenERPOutlookPlugin/Resources/Case.png
static/openerp-outlook-plugin/OpenERPOutlookPlugin/Resources/Contact.png
static/openerp-outlook-plugin/OpenERPOutlookPlugin/Resources/Create.png
static/openerp-outlook-plugin/OpenERPOutlookPlugin/Resources/Error.gif
static/openerp-outlook-plugin/OpenERPOutlookPlugin/Resources/Invoice.png
static/openerp-outlook-plugin/OpenERPOutlookPlugin/Resources/Move.gif
static/openerp-outlook-plugin/OpenERPOutlookPlugin/Resources/MoveDown.png
static/openerp-outlook-plugin/OpenERPOutlookPlugin/Resources/MoveLeft.png
static/openerp-outlook-plugin/OpenERPOutlookPlugin/Resources/OpenERP_icon.ico
static/openerp-outlook-plugin/OpenERPOutlookPlugin/Resources/Partner.png
static/openerp-outlook-plugin/OpenERPOutlookPlugin/Resources/Product.png
static/openerp-outlook-plugin/OpenERPOutlookPlugin/Resources/Project.png
static/openerp-outlook-plugin/OpenERPOutlookPlugin/Resources/Sale.png
static/openerp-outlook-plugin/OpenERPOutlookPlugin/Resources/Search.gif
static/openerp-outlook-plugin/OpenERPOutlookPlugin/Resources/Success.gif
